rclcd_drivers/__init__.py
rclcd_drivers/commands.py
rclcd_drivers/pin.py
rc_lcd_drivers-1.0.0.dist-info/LICENSE
rc_lcd_drivers-1.0.0.dist-info/METADATA
rc_lcd_drivers-1.0.0.dist-info/WHEEL
rc_lcd_drivers-1.0.0.dist-info/top_level.txt
rc_lcd_drivers-1.0.0.dist-info/RECORD
